django_progress_timeline-0.2.dist-info/DESCRIPTION.rst
django_progress_timeline-0.2.dist-info/METADATA
django_progress_timeline-0.2.dist-info/RECORD
django_progress_timeline-0.2.dist-info/WHEEL
django_progress_timeline-0.2.dist-info/metadata.json
django_progress_timeline-0.2.dist-info/top_level.txt
progress_timeline/__init__.py
progress_timeline/admin.py
progress_timeline/apps.py
progress_timeline/factories.py
progress_timeline/fields.py
progress_timeline/models.py
progress_timeline/tests.py
progress_timeline/urls.py
progress_timeline/views.py
progress_timeline/migrations/0001_initial.py
progress_timeline/migrations/__init__.py
progress_timeline/static/jquery-3.3.1.min.js
progress_timeline/static/css/progress_timeline/style.css
progress_timeline/static/farbtastic/.DS_Store
progress_timeline/static/farbtastic/CHANGELOG.html
progress_timeline/static/farbtastic/LICENSE.txt
progress_timeline/static/farbtastic/README.html
progress_timeline/static/farbtastic/demo1.html
progress_timeline/static/farbtastic/demo2.html
progress_timeline/static/farbtastic/farbtastic.css
progress_timeline/static/farbtastic/farbtastic.js
progress_timeline/static/farbtastic/marker.png
progress_timeline/static/farbtastic/mask.png
progress_timeline/static/farbtastic/wheel.png
progress_timeline/static/js/progress_timeline/.js.js.swp
progress_timeline/static/js/progress_timeline/js.js
progress_timeline/templates/.color.html.swp
progress_timeline/templates/color.html
progress_timeline/templates/progress_timeline/progresstimeline.html
progress_timeline/templates/progress_timeline/progresstimeline_detail.html
progress_timeline/templatetags/__init__.py
progress_timeline/templatetags/progress_timeline_tags.py
